pytvfemd/LICENSE
pytvfemd/__init__.py
pytvfemd/pytvfemd.py
pytvfemd-0.3.14.dist-info/LICENSE
pytvfemd-0.3.14.dist-info/METADATA
pytvfemd-0.3.14.dist-info/WHEEL
pytvfemd-0.3.14.dist-info/top_level.txt
pytvfemd-0.3.14.dist-info/RECORD
